{
  "abilities": [
    {
      "name": "solid-rock",
      "url": "https://thepokeapi.com/ability/solid-rock",
      "is_hidden": false,
      "slot": 1
    },
    {
      "name": "sturdy",
      "url": "https://thepokeapi.com/ability/sturdy",
      "is_hidden": false,
      "slot": 2
    },
    {
      "name": "swift-swim",
      "url": "https://thepokeapi.com/ability/swift-swim",
      "is_hidden": true,
      "slot": 3
    }
  ],
  "capture_rate": 45,
  "color": "blue",
  "damage_multipliers": {
    "normal": 0,
    "fire": 0,
    "water": 1,
    "electric": 2,
    "grass": 4,
    "ice": 0,
    "fighting": 2,
    "poison": 0,
    "ground": 2,
    "flying": 0,
    "psychic": 1,
    "bug": 1,
    "rock": 1,
    "ghost": 1,
    "dragon": 1,
    "dark": 1,
    "steel": 1,
    "fairy": 1
  },
  "description": "Its hunting grounds encompassed a broad area, from the land to more than half a mile deep in the ocean.",
  "egg_groups": [
    "water1",
    "water3"
  ],
  "evolution_chain": [
    [
      "tirtouga"
    ],
    [
      "carracosta"
    ]
  ],
  "evolves_from_species": null,
  "growth_rate": "medium",
  "height": 28,
  "id": 564,
  "is_baby": false,
  "is_legendary": false,
  "is_mythical": false,
  "moves": [
    {
      "name": "slam",
      "tm": false,
      "level": null
    },
    {
      "name": "body-slam",
      "tm": false,
      "level": null
    },
    {
      "name": "bite",
      "level": 8,
      "tm": false
    },
    {
      "name": "water-gun",
      "level": 1,
      "tm": false
    },
    {
      "name": "hydro-pump",
      "level": 51,
      "tm": false
    },
    {
      "name": "surf",
      "tm": true,
      "level": null
    },
    {
      "name": "ice-beam",
      "tm": true,
      "level": null
    },
    {
      "name": "blizzard",
      "tm": true,
      "level": null
    },
    {
      "name": "strength",
      "tm": true,
      "level": null
    },
    {
      "name": "rock-throw",
      "tm": false,
      "level": null
    },
    {
      "name": "earthquake",
      "tm": true,
      "level": null
    },
    {
      "name": "dig",
      "tm": true,
      "level": null
    },
    {
      "name": "toxic",
      "tm": true,
      "level": null
    },
    {
      "name": "double-team",
      "tm": true,
      "level": null
    },
    {
      "name": "withdraw",
      "level": 1,
      "tm": false
    },
    {
      "name": "bide",
      "level": 1,
      "tm": false
    },
    {
      "name": "waterfall",
      "tm": true,
      "level": null
    },
    {
      "name": "rest",
      "tm": true,
      "level": null
    },
    {
      "name": "rock-slide",
      "level": 45,
      "tm": false
    },
    {
      "name": "substitute",
      "tm": true,
      "level": null
    },
    {
      "name": "snore",
      "level": 0,
      "tm": false
    },
    {
      "name": "curse",
      "level": 35,
      "tm": false
    },
    {
      "name": "flail",
      "tm": false,
      "level": null
    },
    {
      "name": "protect",
      "level": 11,
      "tm": false
    },
    {
      "name": "icy-wind",
      "level": 0,
      "tm": false
    },
    {
      "name": "sandstorm",
      "tm": true,
      "level": null
    },
    {
      "name": "rollout",
      "level": 5,
      "tm": false
    },
    {
      "name": "swagger",
      "tm": true,
      "level": null
    },
    {
      "name": "attract",
      "tm": true,
      "level": null
    },
    {
      "name": "sleep-talk",
      "level": 0,
      "tm": false
    },
    {
      "name": "return",
      "tm": true,
      "level": null
    },
    {
      "name": "frustration",
      "tm": true,
      "level": null
    },
    {
      "name": "iron-tail",
      "level": 0,
      "tm": false
    },
    {
      "name": "hidden-power",
      "tm": true,
      "level": null
    },
    {
      "name": "rain-dance",
      "level": 48,
      "tm": false
    },
    {
      "name": "crunch",
      "level": 21,
      "tm": false
    },
    {
      "name": "ancient-power",
      "level": 18,
      "tm": false
    },
    {
      "name": "rock-smash",
      "tm": true,
      "level": null
    },
    {
      "name": "whirlpool",
      "tm": false,
      "level": null
    },
    {
      "name": "facade",
      "tm": true,
      "level": null
    },
    {
      "name": "knock-off",
      "tm": false,
      "level": null
    },
    {
      "name": "secret-power",
      "tm": true,
      "level": null
    },
    {
      "name": "dive",
      "tm": true,
      "level": null
    },
    {
      "name": "rock-tomb",
      "tm": true,
      "level": null
    },
    {
      "name": "iron-defense",
      "tm": false,
      "level": null
    },
    {
      "name": "block",
      "level": 0,
      "tm": false
    },
    {
      "name": "water-pulse",
      "tm": false,
      "level": null
    },
    {
      "name": "brine",
      "level": 28,
      "tm": false
    },
    {
      "name": "guard-swap",
      "tm": false,
      "level": null
    },
    {
      "name": "rock-polish",
      "tm": true,
      "level": null
    },
    {
      "name": "aqua-tail",
      "level": 41,
      "tm": false
    },
    {
      "name": "earth-power",
      "level": 0,
      "tm": false
    },
    {
      "name": "zen-headbutt",
      "level": 0,
      "tm": false
    },
    {
      "name": "stone-edge",
      "tm": true,
      "level": null
    },
    {
      "name": "stealth-rock",
      "level": 0,
      "tm": false
    },
    {
      "name": "aqua-jet",
      "level": 15,
      "tm": false
    },
    {
      "name": "wide-guard",
      "level": 25,
      "tm": false
    },
    {
      "name": "smack-down",
      "level": 31,
      "tm": false
    },
    {
      "name": "round",
      "tm": true,
      "level": null
    },
    {
      "name": "scald",
      "tm": true,
      "level": null
    },
    {
      "name": "shell-smash",
      "level": 38,
      "tm": false
    },
    {
      "name": "bulldoze",
      "tm": true,
      "level": null
    },
    {
      "name": "confide",
      "tm": true,
      "level": null
    },
    {
      "name": "liquidation",
      "tm": false,
      "level": null
    }
  ],
  "name": "tirtouga",
  "names": {
    "french": "Carapagos",
    "german": "Galapaflos",
    "spanish": "Tirtouga",
    "italian": "Tirtouga",
    "english": "Tirtouga",
    "japanese": "\u30d7\u30ed\u30c8\u30fc\u30ac"
  },
  "pokedex_numbers": {
    "national": 564,
    "original-unova": 70,
    "updated-unova": 126,
    "original-alola": 194,
    "original-akala": 121,
    "updated-alola": 241,
    "updated-akala": 142,
    "crown-tundra": 147,
    "kanto": null,
    "original-johto": null,
    "updated-johto": null,
    "kalos-central": null,
    "isle-of-armor": null,
    "updated-kanto": null,
    "conquest-gallery": null,
    "galar": null,
    "original-melemele": null,
    "updated-melemele": null,
    "original-ulaula": null,
    "original-poni": null,
    "updated-ulaula": null,
    "updated-poni": null,
    "kalos-mountain": null,
    "hoenn": null,
    "original-sinnoh": null,
    "extended-sinnoh": null,
    "updated-hoenn": null,
    "kalos-coastal": null
  },
  "region": "unova",
  "region_id": 5,
  "shape": "quadruped",
  "species": "Prototurtle Pok\u00e9mon",
  "sprites": {
    "default": "https://raw.githubusercontent.com/hostedposted/PokemonData/master/sprites/pokemon/564.png",
    "shiny": "https://raw.githubusercontent.com/hostedposted/PokemonData/master/sprites/pokemon/shiny/564.png"
  },
  "stats": [
    {
      "name": "hp",
      "base_stat": 54
    },
    {
      "name": "attack",
      "base_stat": 78
    },
    {
      "name": "defense",
      "base_stat": 103
    },
    {
      "name": "special-attack",
      "base_stat": 53
    },
    {
      "name": "special-defense",
      "base_stat": 45
    },
    {
      "name": "speed",
      "base_stat": 22
    }
  ],
  "types": [
    {
      "name": "water",
      "url": "https://thepokeapi.com/type/water"
    },
    {
      "name": "rock",
      "url": "https://thepokeapi.com/type/rock"
    }
  ],
  "weight_kilograms": 16,
  "weight_pounds": 36
}