{
  "abilities": [
    {
      "name": "levitate",
      "is_hidden": false,
      "slot": 1
    }
  ],
  "capture_rate": 225,
  "color": "black",
  "damage_multipliers": {
    "normal": 1,
    "fire": 1,
    "water": 1,
    "electric": 1,
    "grass": 1,
    "ice": 1,
    "fighting": 0,
    "poison": 1,
    "ground": 1,
    "flying": 1,
    "psychic": 0,
    "bug": 4,
    "rock": 1,
    "ghost": 4,
    "dragon": 1,
    "dark": 4,
    "steel": 1,
    "fairy": 1
  },
  "description": "This Pok\u00e9mon is shaped like ancient writing. It is a mystery as to which came first, the ancient writings or the various Unown. Research into this topic is ongoing but nothing is known.",
  "egg_groups": [
    "no-eggs"
  ],
  "evolution_chain": [
    [
      "unown"
    ]
  ],
  "evolves_from_species": null,
  "growth_rate": "medium",
  "height": 20,
  "id": 201,
  "in_games": [
    "national",
    "original-johto",
    "original-sinnoh",
    "extended-sinnoh",
    "updated-johto"
  ],
  "is_baby": false,
  "is_legendary": false,
  "is_mythical": false,
  "moves": [
    {
      "name": "hidden-power",
      "level": 1,
      "tm": false
    }
  ],
  "name": "unown",
  "names": {
    "french": "Zarbi",
    "german": "Icognito",
    "spanish": "Unown",
    "italian": "Unown",
    "english": "Unown",
    "japanese": "\u30a2\u30f3\u30ce\u30fc\u30f3"
  },
  "pokedex_numbers": {
    "national": 201,
    "original-johto": 61,
    "original-sinnoh": 114,
    "extended-sinnoh": 114,
    "updated-johto": 61
  },
  "region": "johto",
  "region_id": 2,
  "shape": "ball",
  "species": "Symbol Pok\u00e9mon",
  "sprites": {
    "default": "https://hostedposted.github.io/api/sprites/pokemon/201.png",
    "shiny": "https://hostedposted.github.io/api/sprites/pokemon/shiny/201.png"
  },
  "stats": [
    {
      "name": "hp",
      "base_stat": 48
    },
    {
      "name": "attack",
      "base_stat": 72
    },
    {
      "name": "defense",
      "base_stat": 48
    },
    {
      "name": "special-attack",
      "base_stat": 72
    },
    {
      "name": "special-defense",
      "base_stat": 48
    },
    {
      "name": "speed",
      "base_stat": 48
    }
  ],
  "types": [
    "psychic"
  ],
  "weight_kilograms": 5,
  "weight_pounds": 11
}